dvc_data/__init__.py
dvc_data/__main__.py
dvc_data/callbacks.py
dvc_data/cli.py
dvc_data/compat.py
dvc_data/fs.py
dvc_data/fsutils.py
dvc_data/json_compat.py
dvc_data/py.typed
dvc_data/repo.py
dvc_data/hashfile/__init__.py
dvc_data/hashfile/_ignore.py
dvc_data/hashfile/_progress.py
dvc_data/hashfile/build.py
dvc_data/hashfile/cache.py
dvc_data/hashfile/checkout.py
dvc_data/hashfile/diff.py
dvc_data/hashfile/gc.py
dvc_data/hashfile/hash.py
dvc_data/hashfile/hash_info.py
dvc_data/hashfile/istextfile.py
dvc_data/hashfile/meta.py
dvc_data/hashfile/obj.py
dvc_data/hashfile/state.py
dvc_data/hashfile/status.py
dvc_data/hashfile/transfer.py
dvc_data/hashfile/tree.py
dvc_data/hashfile/utils.py
dvc_data/hashfile/db/__init__.py
dvc_data/hashfile/db/index.py
dvc_data/hashfile/db/local.py
dvc_data/hashfile/db/migrate.py
dvc_data/hashfile/db/reference.py
dvc_data/index/__init__.py
dvc_data/index/add.py
dvc_data/index/build.py
dvc_data/index/checkout.py
dvc_data/index/collect.py
dvc_data/index/diff.py
dvc_data/index/fetch.py
dvc_data/index/index.py
dvc_data/index/push.py
dvc_data/index/save.py
dvc_data/index/serialize.py
dvc_data/index/update.py
dvc_data/index/view.py
dvc_data-3.18.1.dist-info/licenses/LICENSE
dvc_data-3.18.1.dist-info/METADATA
dvc_data-3.18.1.dist-info/WHEEL
dvc_data-3.18.1.dist-info/entry_points.txt
dvc_data-3.18.1.dist-info/top_level.txt
dvc_data-3.18.1.dist-info/RECORD
