Metadata-Version: 2.4
Name: dvc-data
Version: 3.18.1
Summary: DVC's data management subsystem
Author-email: Iterative <support@dvc.org>
License-Expression: Apache-2.0
Project-URL: Issues, https://github.com/iterative/dvc-data/issues
Project-URL: Source, https://github.com/iterative/dvc-data
Classifier: Programming Language :: Python :: 3
Classifier: Programming Language :: Python :: 3.9
Classifier: Programming Language :: Python :: 3.10
Classifier: Programming Language :: Python :: 3.11
Classifier: Programming Language :: Python :: 3.12
Classifier: Programming Language :: Python :: 3.13
Classifier: Programming Language :: Python :: 3.14
Classifier: Development Status :: 4 - Beta
Requires-Python: >=3.9
License-File: LICENSE
Requires-Dist: attrs>=21.3.0
Requires-Dist: dictdiffer>=0.8.1
Requires-Dist: diskcache>=5.2.1
Requires-Dist: dvc-objects<6,>=5.2
Requires-Dist: fsspec>=2024.2.0
Requires-Dist: funcy>=1.14; python_version < "3.12"
Requires-Dist: pygtrie>=2.3.2
Requires-Dist: sqltrie<1,>=0.11.0
Requires-Dist: tqdm<5,>=4.63.1
Requires-Dist: orjson<4,>=3; implementation_name == "cpython"
Provides-Extra: cli
Requires-Dist: typer-slim>=0.12; extra == "cli"
Provides-Extra: all
Requires-Dist: dvc-data[cli]; extra == "all"
Provides-Extra: tests
Requires-Dist: pytest<10,>=7; extra == "tests"
Requires-Dist: pytest-cov>=4.1.0; extra == "tests"
Requires-Dist: pytest-mock; extra == "tests"
Requires-Dist: pytest-benchmark>=4; extra == "tests"
Provides-Extra: dev
Requires-Dist: dvc-data[all]; extra == "dev"
Requires-Dist: dvc-data[tests]; extra == "dev"
Requires-Dist: mypy==1.19.1; extra == "dev"
Requires-Dist: types-tqdm; extra == "dev"
Dynamic: license-file
